aeronavx/__init__.py
aeronavx/exceptions.py
aeronavx/api/__init__.py
aeronavx/api/server.py
aeronavx/cli/__init__.py
aeronavx/cli/main.py
aeronavx/core/__init__.py
aeronavx/core/airports.py
aeronavx/core/analytics.py
aeronavx/core/distance.py
aeronavx/core/emissions.py
aeronavx/core/emissions_v2.py
aeronavx/core/geodesy.py
aeronavx/core/geospatial_advanced.py
aeronavx/core/loader.py
aeronavx/core/network_intelligence.py
aeronavx/core/passenger_experience.py
aeronavx/core/routing.py
aeronavx/core/search.py
aeronavx/core/synthetic_routes.py
aeronavx/core/timezone.py
aeronavx/core/weather.py
aeronavx/data/airports.csv
aeronavx/data/airports_minimal.csv
aeronavx/models/__init__.py
aeronavx/models/airport.py
aeronavx/models/runway.py
aeronavx/utils/__init__.py
aeronavx/utils/cache.py
aeronavx/utils/constants.py
aeronavx/utils/logging.py
aeronavx/utils/spatial_index.py
aeronavx/utils/units.py
aeronavx/utils/validators.py
aeronavx-2.0.5.dist-info/licenses/LICENSE
aeronavx-2.0.5.dist-info/METADATA
aeronavx-2.0.5.dist-info/WHEEL
aeronavx-2.0.5.dist-info/entry_points.txt
aeronavx-2.0.5.dist-info/top_level.txt
aeronavx-2.0.5.dist-info/RECORD
