Metadata-Version: 2.4
Name: aeronavx
Version: 2.0.5
Summary: Production-grade aviation analytics library: 84k+ airports, network intelligence, synthetic routes, emissions analysis, jet lag prediction, and geo-spatial computations
Author-email: Teyfik OZ <teyfikoz@example.com>
License: MIT
Project-URL: Homepage, https://github.com/teyfikoz/AeroNavX
Project-URL: Repository, https://github.com/teyfikoz/AeroNavX
Project-URL: Documentation, https://github.com/teyfikoz/AeroNavX/docs
Project-URL: Issues, https://github.com/teyfikoz/AeroNavX/issues
Keywords: airport,aviation,geodesy,geography,distance,routing,network-analysis,emissions,jet-lag,flight-planning,aviation-analytics
Classifier: Development Status :: 5 - Production/Stable
Classifier: Intended Audience :: Developers
Classifier: Intended Audience :: Science/Research
Classifier: License :: OSI Approved :: MIT License
Classifier: Programming Language :: Python :: 3
Classifier: Programming Language :: Python :: 3.10
Classifier: Programming Language :: Python :: 3.11
Classifier: Programming Language :: Python :: 3.12
Classifier: Topic :: Scientific/Engineering :: GIS
Classifier: Topic :: Scientific/Engineering :: Information Analysis
Requires-Python: >=3.10
License-File: LICENSE
Provides-Extra: dev
Requires-Dist: pytest>=7.0; extra == "dev"
Requires-Dist: pytest-cov>=4.0; extra == "dev"
Requires-Dist: black>=23.0; extra == "dev"
Requires-Dist: ruff>=0.1.0; extra == "dev"
Provides-Extra: full
Requires-Dist: pandas>=2.0; extra == "full"
Requires-Dist: scipy>=1.10; extra == "full"
Requires-Dist: rapidfuzz>=3.0; extra == "full"
Requires-Dist: timezonefinder>=6.0; extra == "full"
Requires-Dist: requests>=2.31; extra == "full"
Provides-Extra: api
Requires-Dist: fastapi>=0.104; extra == "api"
Requires-Dist: uvicorn[standard]>=0.24; extra == "api"
Provides-Extra: all
Requires-Dist: pandas>=2.0; extra == "all"
Requires-Dist: scipy>=1.10; extra == "all"
Requires-Dist: rapidfuzz>=3.0; extra == "all"
Requires-Dist: timezonefinder>=6.0; extra == "all"
Requires-Dist: requests>=2.31; extra == "all"
Requires-Dist: fastapi>=0.104; extra == "all"
Requires-Dist: uvicorn[standard]>=0.24; extra == "all"
Dynamic: license-file
